{
    "spider": "./spider.jar",
    "wallpaper": "https://i0.hdslb.com/bfs/new_dyn/d512eadb60be5cf999b0df5074260ece522628429.jpg@.webp",
    "logo": "https://i0.hdslb.com/bfs/new_dyn/4870f78c8757be6d9ab2614999b0eff61083307557.gif",
    "sites": [
        {
            "key": "иұҶз“Ј",
            "name": "рҹ‘Җж—ӯеҸ”в”ғеёҰдҪ дҪ“йӘҢж–°и§Ҷз•Ңрҹ”Қ",
            "type": 3,
            "api": "csp_Douban",
            "searchable": 0,
            "changeable": 0
        },
        {
            "key": "жң¬ең°",
            "name": "рҹ—Ӯжң¬ең°в”ғж–Үд»¶",
            "type": 3,
            "api": "csp_LocalFile",
            "searchable": 0,
            "changeable": 0
        },
        {
            "key": "й…ҚзҪ®дёӯеҝғ",
            "name": "рҹ’»й…ҚзҪ®в”ғдёӯеҝғ",
            "type": 3,
            "api": "csp_Config",
            "searchable": 0,
            "changeable": 0,
            "indexs": 0,
            "style": {
                "type": "rect",
                "ratio": 1.597
            }
        },
        {
            "key": "зғӯж’ӯ",
            "name": "вҳҖпёҸзғӯж’ӯв”ғж—ӯеҸ”",
            "type": 3,
            "api": "csp_AppRJ",
            "searchable": 1,
            "quickSearch": 1,
            "filterable": 0,
            "ext": {
                "url": "http://v.rbotv.cn"
            }
        },
        {
            "key": "жөӘй…·",
            "name": "рҹҸ„вҖҚжөӘй…·в”ғж—ӯеҸ”",
            "type": 3,
            "api": "./py/жөӘй…·.py",
            "ext": "http://43.248.117.123:4680"
        },
        {
            "key": "йҮ‘зүҢ",
            "name": "рҹҘҮйҮ‘зүҢв”ғж—ӯеҸ”",
            "type": 3,
            "api": "csp_Jpys",
            "ext": "https://y2s52n7.com,https://m.hkybqufgh.com,https://m.sizhengxt.com,https://m.9zhoukj.com,https://m.sizhengxt.com,https://m.jiabaide.cn"
        },
        {
            "key": "з§’зңӢ",
            "name": "рҹҚҺиӢ№жһңв”ғж—ӯеҸ”",
            "type": 3,
            "api": "csp_AppGet",
            "ext": {
                "site": "https://mk1080.top/get.txt",
                "dataKey": "c60d88b2eep53za8",
                "dataIv": "c60d88b2eep53za8",
                "token": "4181e508e7a17657d6a6246e70b1b13553e5ae9d8d287dc47000fb2df638dffa",
                "ua": "okhttp/3.14.9"
            }
        },
        {
            "key": "з“ңеӯҗ",
            "name": "рҹҚүз“ңеӯҗв”ғж—ӯеҸ”",
            "type": 3,
            "api": "csp_Gz360",
            "searchable": 1,
            "quickSearch": 1,
            "filterable": 1
        },
        {
            "key": "е°Ҹй•Ү",
            "name": "рҹҘқеҘҮејӮв”ғж—ӯеҸ”",
            "type": 3,
            "api": "csp_XBPQ",
            "ext": "./XBPQ/е°Ҹй•Ү.json"
        },
        {
            "key": "зҢҺжүӢ",
            "name": "рҹҰҠзҒ«зӢҗв”ғж—ӯеҸ”",
            "type": 3,
            "api": "./py/зҢҺжүӢ.py",
            "searchable": 1,
            "changeable": 1,
            "quickSearch": 1,
            "filterable": 1,
            "playerType": 2
        },
        {
            "key": "еҶңж°‘",
            "name": "рҹ‘ЁвҖҚрҹҢҫеҶңж°‘в”ғж—ӯеҸ”",
            "type": 3,
            "api": "csp_XYQHiker",
            "searchable": 1,
            "quickSearch": 1,
            "filterable": 1,
            "ext": "./XBPQ/еҶңж°‘.json"
        },
        {
            "key": "дәәдәә",
            "name": "рҹ•өпёҸвҖҚвҷӮпёҸеҘҪдәәв”ғж—ӯеҸ”",
            "type": 3,
            "api": "./py/дәәдәә.py",
            "searchable": 1,
            "quickSearch": 1,
            "changeable": 1,
            "filterable": 1
        },
        {
            "key": "жҡҙйЈҺиө„жәҗ",
            "name": "рҹҢҖжҡҙйЈҺв”ғж—ӯеҸ”",
            "type": 1,
            "api": "https://bfzyapi.com/api.php/provide/vod/",
            "searchable": 1,
            "quickSearch": 1,
            "categories": [
                "еҠЁдҪңзүҮ",
                "е–ңеү§зүҮ",
                "жҒҗжҖ–зүҮ",
                "з§‘е№»зүҮ",
                "зҲұжғ…зүҮ",
                "еү§жғ…зүҮ",
                "жҲҳдәүзүҮ",
                "зәӘеҪ•зүҮ",
                "еӣҪдә§еү§",
                "ж¬§зҫҺеү§",
                "йҰҷжёҜеү§",
                "йҹ©еӣҪеү§",
                "еҸ°ж№ҫеү§",
                "жө·еӨ–еү§",
                "жі°еӣҪеү§",
                "еҠЁжј«зүҮ",
                "еӣҪдә§еҠЁжј«",
                "ж—Ҙйҹ©еҠЁжј«",
                "ж¬§зҫҺеҠЁжј«",
                "жёҜеҸ°еҠЁжј«",
                "жө·еӨ–еҠЁжј«",
                "еӨ§йҷҶз»јиүә",
                "жёҜеҸ°з»јиүә",
                "ж—Ҙйҹ©з»јиүә",
                "ж¬§зҫҺз»јиүә",
                "еҠЁз”»зүҮ"
            ]
        },
        {
            "key": "еҰӮж„Ҹиө„жәҗ",
            "name": "рҹҺҖеҰӮж„Ҹв”ғж—ӯеҸ”",
            "type": 1,
            "api": "https://cj.rycjapi.com/api.php/provide/vod/",
            "searchable": 1,
            "quickSearch": 1,
            "categories": [
                "еҠЁдҪңзүҮ",
                "е–ңеү§зүҮ",
                "зҲұжғ…зүҮ",
                "з§‘е№»зүҮ",
                "жҒҗжҖ–зүҮ",
                "и®°еҪ•зүҮ",
                "жҲҳдәүзүҮ",
                "еӣҪдә§еү§",
                "йҰҷжёҜеү§",
                "ж—Ҙжң¬еү§",
                "йҹ©еӣҪеү§",
                "ж¬§зҫҺеү§",
                "жі°еӣҪеү§",
                "зҹӯеү§",
                "еӣҪдә§еҠЁжј«",
                "еҠЁз”»зүҮ",
                "ж—Ҙйҹ©еҠЁжј«",
                "з”өеҪұ",
                "з”өи§Ҷеү§"
            ]
        },
        {
            "key": "зӢ¬ж’ӯеә“",
            "name": "рҹ”ҘзӢ¬ж’ӯв”ғж—ӯеҸ”",
            "type": 3,
            "api": "./js/зӢ¬ж’ӯеә“.js"
        },
        {
            "key": "е°Ҹж–‘еҝ«жҳ ",
            "name": "рҹ“Ҫеҝ«жҳ в”ғж—ӯеҸ”",
            "type": 3,
            "api": "csp_PanWebShare",
            "searchable": 1,
            "quickSearch": 1,
            "filterable": 1,
            "changeable": 0,
            "ext": {
                "site": [
                    "http://xsayang.fun:12512",
                    "http://154.201.83.50:12512"
                ]
            }
        },
        {
            "key": "зҺ©еҒ¶е“Ҙе“Ҙ",
            "name": "рҹ‘ҪзҺ©еҒ¶в”ғж—ӯеҸ”",
            "type": 3,
            "api": "csp_Wogg",
            "searchable": 1,
            "quickSearch": 1,
            "filterable": 1,
            "changeable": 0,
            "ext": {
                "site": [
                    "https://www.wogg.net",
                    "https://wogg.333232.xyz",
                    "https://wogg.xxooo.cf",
                    "https://woggpan.888484.xyz"
                ]
            }
        },
        {
            "key": "иңЎз¬”",
            "name": "рҹ’„иңЎз¬”в”ғж—ӯеҸ”",
            "type": 3,
            "api": "csp_PanWebShare",
            "searchable": 1,
            "quickSearch": 1,
            "filterable": 1,
            "changeable": 0,
            "ext": {
                "site": [
                    "http://xiaocge.fun",
                    "http://feimo.fun",
                    "https://feimao666.fun",
                    "http://feimao888.fun",
                    "http://www.labi88.sbs",
                    "http://fmao.site",
                    "http://fmao.shop",
                    "http://xiaocgege.shop"
                ]
            }
        },
        {
            "key": "иҮіиҮ»",
            "name": "рҹҺҘиҮіиҮ»в”ғж—ӯеҸ”",
            "type": 3,
            "api": "csp_PanWebShare",
            "searchable": 1,
            "quickSearch": 1,
            "filterable": 1,
            "changeable": 0,
            "ext": {
                "site": [
                    "https://mihdr.top",
                    "https://www.miqk.cc",
                    "https://xiaomiai.site",
                    "https://xiaomi666.fun",
                    "https://www.mihdr.top",
                    "https://www.zhizhenpan.fun"
                ]
            }
        },
        {
            "key": "жңЁеҒ¶",
            "name": "рҹ“ҰжңЁеҒ¶в”ғж—ӯеҸ”",
            "type": 3,
            "api": "csp_PanWebShare",
            "searchable": 1,
            "quickSearch": 1,
            "filterable": 1,
            "changeable": 0,
            "ext": {
                "site": [
                    "https://123.666291.xyz",
                    "https://666.666291.xyz",
                    "https://www.muou.site",
                    "https://www.muou.asia"
                ]
            }
        },
        {
            "key": "дәҢе°Ҹ",
            "name": "рҹғҸе°ҸдәҢв”ғж—ӯеҸ”",
            "type": 3,
            "api": "csp_PanWebShare",
            "searchable": 1,
            "quickSearch": 1,
            "filterable": 1,
            "changeable": 0,
            "ext": {
                "site": [
                    "https://www.erixaopan.fun",
                    "https://www.wexwp.cc",
                    "https://wexwp.cc",
                    "https://2xiaopan.top",
                    "https://www.2xiaopan.top"
                ]
            }
        },
        {
            "key": "зӣҳеә“",
            "name": "рҹ“Җзӣҳеә“в”ғж—ӯеҸ”",
            "type": 3,
            "api": "csp_PanSou",
            "changeable": 0,
            "searchable": 1,
            "quickSearch": 0,
            "filterable": 0
        },
        {
            "key": "йҹіжө·",
            "name": "рҹ“ҖзүҮеә“в”ғж—ӯеҸ”",
            "type": 3,
            "api": "csp_YinHai",
            "changeable": 0,
            "searchable": 1,
            "quickSearch": 1,
            "filterable": 1
        },
        {
            "key": "зі–жһң",
            "name": "рҹ“ҖеҪұеә“в”ғж—ӯеҸ”",
            "type": 3,
            "api": "csp_TGSou",
            "searchable": 1,
            "changeable": 0
        },
        {
            "key": "жҙҫжҗң",
            "name": "рҹ’ҝзӣҳжҗңв”ғж—ӯеҸ”",
            "type": 3,
            "api": "csp_PanSouPan",
            "changeable": 0,
            "searchable": 1,
            "quickSearch": 0,
            "filterable": 0
        },
        {
            "key": "зүҮжҗң",
            "name": "рҹ’ҝзүҮжҗңв”ғж—ӯеҸ”",
            "type": 3,
            "api": "csp_PianSo",
            "changeable": 0,
            "searchable": 1,
            "quickSearch": 1,
            "filterable": 1
        },
        {
            "key": "зұіжҗң",
            "name": "рҹ’ҝзұіжҗңв”ғж—ӯеҸ”",
            "type": 3,
            "api": "csp_MiSou",
            "changeable": 0
        },
        {
            "key": "зҷҫй…·",
            "name": "рҹҺҜдҪ°еә“в”ғж—ӯеҸ”",
            "type": 3,
            "api": "csp_Baiku",
            "changeable": 0
        },
        {
            "key": "жёЎзӣҳзӨҫ",
            "name": "рҹҺҜдҪ°жёЎв”ғж—ӯеҸ”",
            "type": 3,
            "api": "csp_PanWebQu",
            "searchable": 1,
            "quickSearch": 1,
            "filterable": 1,
            "changeable": 0,
            "style": {
                "type": "list",
                "ratio": 1.433
            },
            "ext": {
                "url": "https://www.qupanshe.com"
            }
        },
        {
            "key": "йҹіжө·жёЎеЁҳ",
            "name": "рҹҺҜжёЎеЁҳв”ғж—ӯеҸ”",
            "type": 3,
            "api": "csp_YinHaiBaidu",
            "changeable": 0,
            "searchable": 1,
            "quickSearch": 1,
            "filterable": 1
        },
        {
            "key": "еӨёзҲ¶",
            "name": "рҹ§ҝеӨёзҲ¶в”ғж—ӯеҸ”",
            "type": 3,
            "api": "csp_PanWebShareCloudXKF",
            "searchable": 1,
            "quickSearch": 1,
            "filterable": 1,
            "changeable": 0,
            "style": {
                "type": "list",
                "ratio": 1.433
            },
            "ext": "./json/xkf.json"
        },
        {
            "key": "еӨёеңҲ",
            "name": "рҹ§ҝеӨёеңҲв”ғж—ӯеҸ”",
            "type": 3,
            "api": "csp_PanWebShareCloudKQ",
            "searchable": 1,
            "quickSearch": 1,
            "filterable": 1,
            "changeable": 0,
            "style": {
                "type": "list",
                "ratio": 1.433
            },
            "ext": "./json/kq.json"
        },
        {
            "key": "и¶Јзӣҳжҗң",
            "name": "рҹ§ҝеӨёжҗңв”ғж—ӯеҸ”",
            "type": 3,
            "api": "csp_QuPanSo",
            "changeable": 0
        },
        {
            "key": "зӣҳеә“еӨёе…Ӣ",
            "name": "рҹҺ¬еӨёеә“в”ғж—ӯеҸ”",
            "type": 3,
            "api": "csp_PankuQuark",
            "changeable": 0,
            "searchable": 1,
            "quickSearch": 1,
            "filterable": 1
        },
        {
            "key": "йҹіжө·еӨёе…Ӣ",
            "name": "рҹҺ¬еӨёеҪұв”ғж—ӯеҸ”",
            "type": 3,
            "api": "csp_YinHaiQuark",
            "changeable": 0,
            "searchable": 1,
            "quickSearch": 1,
            "filterable": 1
        },
        {
            "key": "зӣҳжҗңеӨёе…Ӣ",
            "name": "рҹҺ¬еӨёзӣҳв”ғж—ӯеҸ”",
            "type": 3,
            "api": "csp_PanSouQuark",
            "changeable": 0,
            "searchable": 1,
            "quickSearch": 1,
            "filterable": 1
        },
        {
            "key": "жө·з»ө",
            "name": "рҹӣ©еӨ©зӣҠв”ғж—ӯеҸ”",
            "type": 3,
            "api": "csp_PanWebShareCloudHM",
            "searchable": 1,
            "quickSearch": 1,
            "filterable": 1,
            "changeable": 0,
            "style": {
                "type": "list",
                "ratio": 1.433
            },
            "ext": "./json/hm.json"
        },
        {
            "key": "йӣ·йІё",
            "name": "вңҲпёҸеӨ©йҖёв”ғж—ӯеҸ”",
            "type": 3,
            "api": "csp_PanWebShareCloudLJ",
            "searchable": 1,
            "quickSearch": 1,
            "filterable": 1,
            "changeable": 0,
            "style": {
                "type": "list",
                "ratio": 1.433
            },
            "ext": "./json/lj.json"
        },
        {
            "key": "йҹіжө·еӨ©зҝј",
            "name": "рҹҡҖзҝјжҗңв”ғж—ӯеҸ”",
            "type": 3,
            "api": "csp_YinHaiTianyi",
            "changeable": 0,
            "searchable": 1,
            "quickSearch": 1,
            "filterable": 1
        },
        {
            "key": "123",
            "name": "вӣ”дәҢдёүв”ғж—ӯеҸ”",
            "type": 3,
            "api": "csp_PanWebShareCloud123",
            "searchable": 1,
            "quickSearch": 1,
            "filterable": 1,
            "changeable": 0,
            "style": {
                "type": "list",
                "ratio": 1.433
            },
            "ext": "./json/123.json"
        },
        {
            "key": "йҹіжө·дјҳжұҗ",
            "name": "рҹҺЁдјҳжұҗв”ғж—ӯеҸ”",
            "type": 3,
            "api": "csp_YinHaiUC",
            "changeable": 0,
            "searchable": 1,
            "quickSearch": 1,
            "filterable": 1
        },
        {
            "key": "еӨ©зҝј",
            "name": "рҹӣёйҖёжҗңв”ғж—ӯеҸ”",
            "type": 3,
            "api": "csp_TianYiSo",
            "changeable": 0
        },
        {
            "key": "ж¬§е“Ҙ",
            "name": "вӯ•ж¬§е“Ҙв”ғж—ӯеҸ”",
            "type": 3,
            "api": "csp_PanWebShare",
            "searchable": 1,
            "quickSearch": 1,
            "filterable": 1,
            "changeable": 0,
            "ext": {
                "site": [
                    "https://woog.nxog.eu.org",
                    "https://woog.nxog.fun",
                    "https://woog.nxog.de5.net",
                    "https://woog.430520.xyz"
                ]
            }
        },
        {
            "key": "иҷҺж–‘",
            "name": "рҹҗҜе°ҸиҷҺв”ғж—ӯеҸ”",
            "type": 3,
            "api": "csp_PanWebShare",
            "searchable": 1,
            "quickSearch": 1,
            "filterable": 1,
            "changeable": 0,
            "ext": {
                "site": [
                    "http://103.45.162.207:20720",
                    "http://xhban.xyz:20720",
                    "http://154.222.27.33:20720"
                ]
            }
        },
        {
            "key": "ж··еҗҲжҗң",
            "name": "рҹҺҰиҒҡжҗңв”ғж—ӯеҸ”",
            "type": 3,
            "api": "csp_HunHePan",
            "changeable": 0
        },
        {
            "key": "иҚҗзүҮ",
            "name": "рҹ§ІиҚҗзүҮв”ғж—ӯеҸ”",
            "api": "csp_Jianpian",
            "changeable": 0,
            "type": 3,
            "ext": "https://api.ztcgi.com"
        },
        {
            "key": "еӨ©е Ӯ",
            "name": "рҹ§ІеӨ©е Ӯв”ғж—ӯеҸ”",
            "type": 3,
            "api": "csp_DyGod",
            "changeable": 0,
            "searchable": 1,
            "quickSearch": 1,
            "filterable": 1
        },
        {
            "key": "80S",
            "name": "рҹ§ІзӢҗзӢёв”ғж—ӯеҸ”",
            "type": 3,
            "api": "csp_BLSGod",
            "changeable": 0,
            "playerType": 2,
            "searchable": 1,
            "quickSearch": 1,
            "filterable": 1
        },
        {
            "key": "е“”е“©е“”е“©жҲҸжӣІ",
            "name": "рҹ…ұпёҸе“”е“©в”ғжҲҸжӣІ",
            "type": 3,
            "api": "csp_Bili",
            "searchable": 0,
            "quickSearch": 0,
            "filterable": 0,
            "changeable": 0,
            "ext": {
                "cookie": "http://127.0.0.1:9978/file/TVBox/bili_cookie.txt",
                "json": "./json/е“”е“©е“”е“©жҲҸжӣІ.json"
            },
            "style": {
                "type": "rect",
                "ratio": 1.597
            }
        },
        {
            "key": "е“”е“©е“”е“©зӣёеЈ°",
            "name": "рҹ…ұпёҸе“”е“©в”ғзӣёеЈ°",
            "type": 3,
            "api": "csp_Bili",
            "searchable": 0,
            "quickSearch": 0,
            "filterable": 0,
            "changeable": 0,
            "ext": {
                "cookie": "http://127.0.0.1:9978/file/TVBox/bili_cookie.txt",
                "json": "./json/е“”е“©е“”е“©зӣёеЈ°.json"
            },
            "style": {
                "type": "rect",
                "ratio": 1.597
            }
        },
        {
            "key": "е“”е“©е“”е“©е°Ҹе“Ғ",
            "name": "рҹ…ұпёҸе“”е“©в”ғе°Ҹе“Ғ",
            "type": 3,
            "api": "csp_Bili",
            "searchable": 0,
            "quickSearch": 0,
            "filterable": 0,
            "changeable": 0,
            "ext": {
                "cookie": "http://127.0.0.1:9978/file/TVBox/bili_cookie.txt",
                "json": "./json/е“”е“©е“”е“©е°Ҹе“Ғ.json"
            },
            "style": {
                "type": "rect",
                "ratio": 1.597
            }
        },
        {
            "key": "е°‘е„ҝж•ҷиӮІ",
            "name": "рҹҶҺе“”е“©в”ғе„ҝз«Ҙ",
            "type": 3,
            "api": "csp_Bili",
            "searchable": 0,
            "quickSearch": 0,
            "changeable": 0,
            "filterable": 1,
            "ext": {
                "json": "./json/е°‘е„ҝж•ҷиӮІ.json",
                "cookie": "http://127.0.0.1:9978/file/TVBox/bili_cookie.txt"
            },
            "style": {
                "type": "rect",
                "ratio": 1.597
            }
        },
        {
            "key": "е“”е“©и§Ҷйў‘",
            "name": "рҹҶҺе“”е“©в”ғи§Ҷйў‘",
            "type": 3,
            "api": "csp_BiliYS",
            "searchable": 0,
            "quickSearch": 0,
            "filterable": 0,
            "changeable": 0,
            "style": {
                "type": "rect",
                "ratio": 1.433
            },
            "ext": {
                "json": "./json/е“”е“©и§Ҷйў‘.json",
                "cookie": "http://127.0.0.1:9978/file/TVBox/bili_cookie.txt"
            }
        },
        {
            "key": "е“”е“©еҗҲйӣҶ",
            "name": "рҹҶҺе“”е“©в”ғеҗҲйӣҶ",
            "type": 3,
            "api": "csp_Bili",
            "searchable": 0,
            "quickSearch": 0,
            "filterable": 0,
            "changeable": 0,
            "style": {
                "type": "rect",
                "ratio": 1.433
            },
            "ext": {
                "json": "./json/е“”е“©еҗҲйӣҶ.json",
                "cookie": "http://127.0.0.1:9978/file/TVBox/bili_cookie.txt"
            }
        },
        {
            "key": "еӨёе®ўдә‘зӣҳ",
            "name": "рҹ—ӮжҲ‘зҡ„в”ғеӨёе®ў",
            "type": 3,
            "api": "csp_PanQuark",
            "searchable": 0,
            "filterable": 0,
            "changeable": 0,
            "style": {
                "type": "list",
                "ratio": 1.433
            },
            "ext": "./json/quarkShare.json"
        },
        {
            "key": "дјҳжұҗдә‘зӣҳ",
            "name": "рҹ—ӮжҲ‘зҡ„в”ғдјҳжұҗ",
            "type": 3,
            "api": "csp_PanUc",
            "searchable": 0,
            "filterable": 0,
            "changeable": 0,
            "style": {
                "type": "list",
                "ratio": 1.433
            },
            "ext": "./json/ucShare.json"
        },
        {
            "key": "дҪ°жёЎдә‘зӣҳ",
            "name": "рҹ—ӮжҲ‘зҡ„в”ғдҪ°жёЎ",
            "type": 3,
            "api": "csp_PanBaiDu",
            "searchable": 0,
            "filterable": 0,
            "changeable": 0,
            "style": {
                "type": "list",
                "ratio": 1.433
            }
        },
        {
            "key": "push_agent",
            "name": "рҹ“ұжүӢжңәв”ғжҺЁйҖҒ",
            "type": 3,
            "api": "csp_Push",
            "searchable": 0,
            "filterable": 0,
            "changeable": 0
        }
    ],
    "parses": [
        {
            "name": "ж—ӯеҸ”4K",
            "type": 1,
            "url": "https://zy.qiaoji8.com/xiafan.php?url=",
            "ext": {
                "flag": [
                    "QD4K",
                    "iyf",
                    "duanju",
                    "gzcj",
                    "GTV",
                    "GZYS",
                    "weggz",
                    "Ace"
                ],
                "header": {
                    "User-Agent": "okhttp/4.9.1"
                }
            }
        }
    ],
    "rules": [
        {
            "name": "еҶңж°‘",
            "hosts": [
                "toutiaovod.com"
            ],
            "regex": [
                "video/tos/cn"
            ]
        },
        {
            "name": "зҒ«еұұ",
            "hosts": [
                "huoshan.com"
            ],
            "regex": [
                "item_id="
            ]
        },
        {
            "name": "жҠ–йҹі",
            "hosts": [
                "douyin.com"
            ],
            "regex": [
                "is_play_url="
            ]
        },
        {
            "name": "йҘӯеӣўзӮ№еҮ»",
            "hosts": [
                "dadagui",
                "freeok",
                "dadagui"
            ],
            "script": [
                "document.querySelector(\"#playleft iframe\").contentWindow.document.querySelector(\"#start\").click();"
            ]
        },
        {
            "name": "жҜӣй©ҙзӮ№еҮ»",
            "hosts": [
                "www.maolvys.com"
            ],
            "script": [
                "document.getElementsByClassName('swal-button swal-button--confirm')[0].click()"
            ]
        },
        {
            "name": "ofiii",
            "hosts": [
                "www.ofiii.com"
            ],
            "script": [
                "const play=document.getElementsByClassName('play_icon')[0],event=new MouseEvent('click',{bubbles:!0,cancelable:!0,view:window,screenX:100,screenY:100,clientX:50,clientY:50,button:0,shiftKey:!1,ctrlKey:!1,altKey:!1,metaKey:!1,modifierState:0});play.dispatchEvent(event);"
            ]
        }
    ],
    "doh": [
        {
            "name": "Google",
            "url": "https://dns.google/dns-query",
            "ips": [
                "8.8.4.4",
                "8.8.8.8"
            ]
        },
        {
            "name": "Cloudflare",
            "url": "https://cloudflare-dns.com/dns-query",
            "ips": [
                "1.1.1.1",
                "1.0.0.1",
                "2606:4700:4700::1111",
                "2606:4700:4700::1001"
            ]
        },
        {
            "name": "AdGuard",
            "url": "https://dns.adguard.com/dns-query",
            "ips": [
                "94.140.14.140",
                "94.140.14.141"
            ]
        },
        {
            "name": "DNSWatch",
            "url": "https://resolver2.dns.watch/dns-query",
            "ips": [
                "84.200.69.80",
                "84.200.70.40"
            ]
        },
        {
            "name": "Quad9",
            "url": "https://dns.quad9.net/dns-quer",
            "ips": [
                "9.9.9.9",
                "149.112.112.112"
            ]
        }
    ],
    "flags": [
        "youku",
        "дјҳй…·",
        "дјҳ й…·",
        "дјҳй…·и§Ҷйў‘",
        "qq",
        "и…ҫи®Ҝ",
        "и…ҫ и®Ҝ",
        "и…ҫи®Ҝи§Ҷйў‘",
        "iqiyi",
        "qiyi",
        "еҘҮиүә",
        "зҲұеҘҮиүә",
        "зҲұ еҘҮ иүә",
        "m1905",
        "xigua",
        "letv",
        "leshi",
        "д№җи§Ҷ",
        "д№җ и§Ҷ",
        "sohu",
        "жҗңзӢҗ",
        "жҗң зӢҗ",
        "жҗңзӢҗи§Ҷйў‘",
        "tudou",
        "pptv",
        "mgtv",
        "иҠ’жһң",
        "imgo",
        "иҠ’жһңTV",
        "иҠ’ жһң T V",
        "bilibili",
        "е“” е“©",
        "е“” е“© е“” е“©"
    ],
    "ijk": [
        {
            "group": "иҪҜи§Јз Ғ",
            "options": [
                {
                    "category": 4,
                    "name": "opensles",
                    "value": "0"
                },
                {
                    "category": 4,
                    "name": "overlay-format",
                    "value": "842225234"
                },
                {
                    "category": 4,
                    "name": "framedrop",
                    "value": "1"
                },
                {
                    "category": 4,
                    "name": "soundtouch",
                    "value": "1"
                },
                {
                    "category": 4,
                    "name": "start-on-prepared",
                    "value": "1"
                },
                {
                    "category": 1,
                    "name": "http-detect-range-support",
                    "value": "0"
                },
                {
                    "category": 1,
                    "name": "fflags",
                    "value": "fastseek"
                },
                {
                    "category": 2,
                    "name": "skip_loop_filter",
                    "value": "48"
                },
                {
                    "category": 4,
                    "name": "reconnect",
                    "value": "1"
                },
                {
                    "category": 4,
                    "name": "enable-accurate-seek",
                    "value": "0"
                },
                {
                    "category": 4,
                    "name": "mediacodec",
                    "value": "0"
                },
                {
                    "category": 4,
                    "name": "mediacodec-auto-rotate",
                    "value": "0"
                },
                {
                    "category": 4,
                    "name": "mediacodec-handle-resolution-change",
                    "value": "0"
                },
                {
                    "category": 4,
                    "name": "mediacodec-hevc",
                    "value": "0"
                },
                {
                    "category": 1,
                    "name": "dns_cache_timeout",
                    "value": "600000000"
                }
            ]
        },
        {
            "group": "зЎ¬и§Јз Ғ",
            "options": [
                {
                    "category": 4,
                    "name": "opensles",
                    "value": "0"
                },
                {
                    "category": 4,
                    "name": "overlay-format",
                    "value": "842225234"
                },
                {
                    "category": 4,
                    "name": "framedrop",
                    "value": "1"
                },
                {
                    "category": 4,
                    "name": "soundtouch",
                    "value": "1"
                },
                {
                    "category": 4,
                    "name": "start-on-prepared",
                    "value": "1"
                },
                {
                    "category": 1,
                    "name": "http-detect-range-support",
                    "value": "0"
                },
                {
                    "category": 1,
                    "name": "fflags",
                    "value": "fastseek"
                },
                {
                    "category": 2,
                    "name": "skip_loop_filter",
                    "value": "48"
                },
                {
                    "category": 4,
                    "name": "reconnect",
                    "value": "1"
                },
                {
                    "category": 4,
                    "name": "enable-accurate-seek",
                    "value": "0"
                },
                {
                    "category": 4,
                    "name": "mediacodec",
                    "value": "1"
                },
                {
                    "category": 4,
                    "name": "mediacodec-auto-rotate",
                    "value": "1"
                },
                {
                    "category": 4,
                    "name": "mediacodec-handle-resolution-change",
                    "value": "1"
                },
                {
                    "category": 4,
                    "name": "mediacodec-hevc",
                    "value": "1"
                },
                {
                    "category": 1,
                    "name": "dns_cache_timeout",
                    "value": "600000000"
                }
            ]
        }
    ],
    "ads": [
        "static-mozai.4gtv.tv"
    ]
}